python_terraform/__init__.py
python_terraform/terraform.py
python_terraform/tfstate.py
python_terraform_wrapper-0.14.0.dist-info/LICENSE.txt
python_terraform_wrapper-0.14.0.dist-info/METADATA
python_terraform_wrapper-0.14.0.dist-info/WHEEL
python_terraform_wrapper-0.14.0.dist-info/top_level.txt
python_terraform_wrapper-0.14.0.dist-info/RECORD
